MANIFEST.in
README
setup.cfg
setup.py
bin/ss-abort
bin/ss-cancel-abort
bin/ss-config-dump
bin/ss-display
bin/ss-execute
bin/ss-get
bin/ss-get-all
bin/ss-login
bin/ss-logout
bin/ss-module-delete
bin/ss-module-download
bin/ss-module-get
bin/ss-module-put
bin/ss-module-upload
bin/ss-node-add
bin/ss-node-remove
bin/ss-random
bin/ss-reports-get
bin/ss-run-get
bin/ss-scale-disk
bin/ss-scale-resize
bin/ss-set
bin/ss-terminate
bin/ss-user-get
bin/ss-user-put
lib/slipstream/Client.py
lib/slipstream/ConfigHolder.py
lib/slipstream/Contextualizer.py
lib/slipstream/HttpClient.py
lib/slipstream/LocalRuntimeConnector.py
lib/slipstream/Logger.py
lib/slipstream/NodeDecorator.py
lib/slipstream/NodeInstance.py
lib/slipstream/SlipStreamHttpClient.py
lib/slipstream/UserInfo.py
lib/slipstream/UtilCommands.py
lib/slipstream/__init__.py
lib/slipstream/__version__.py
lib/slipstream/util.py
lib/slipstream/command/CloudClientCommand.py
lib/slipstream/command/CommandBase.py
lib/slipstream/command/DescribeInstancesCommand.py
lib/slipstream/command/RunInstancesCommand.py
lib/slipstream/command/ServiceOffersCommand.py
lib/slipstream/command/TerminateInstancesCommand.py
lib/slipstream/command/VMCommandBase.py
lib/slipstream/command/VerticalScaleCommandBase.py
lib/slipstream/command/__init__.py
lib/slipstream/commands/NodeInstanceRuntimeParameter.py
lib/slipstream/commands/__init__.py
lib/slipstream/contextualizers/ContextualizerFactory.py
lib/slipstream/contextualizers/__init__.py
lib/slipstream/contextualizers/dummy/LocalContextualizer.py
lib/slipstream/contextualizers/dummy/__init__.py
lib/slipstream/exceptions/Exceptions.py
lib/slipstream/exceptions/__init__.py
lib/slipstream/resources/__init__.py
lib/slipstream/resources/configuration.py
lib/slipstream/resources/reports.py
lib/slipstream/resources/run.py
lib/slipstream/wrappers/BaseWrapper.py
lib/slipstream/wrappers/CloudWrapper.py
lib/slipstream/wrappers/__init__.py
slipstream_client.egg-info/PKG-INFO
slipstream_client.egg-info/SOURCES.txt
slipstream_client.egg-info/dependency_links.txt
slipstream_client.egg-info/namespace_packages.txt
slipstream_client.egg-info/requires.txt
slipstream_client.egg-info/top_level.txt