Metadata-Version: 1.1
Name: slipstream-client
Version: 3.71
Summary: SlipStream end-user client (CLI)
Home-page: http://sixsq.com
Author: SixSq Sarl, (sixsq.com)
Author-email: info@sixsq.com
License: Apache License, Version 2.0
Platform: Any
Classifier: Development Status :: 5 - Production/Stable
Classifier: Intended Audience :: Developers
Classifier: License :: OSI Approved :: Apache Software License
Classifier: Operating System :: Unix
Classifier: Operating System :: Microsoft :: Windows
Classifier: Programming Language :: Python
Classifier: Programming Language :: Python :: 2.6
Classifier: Programming Language :: Python :: 2.7
Classifier: Topic :: Software Development :: Libraries :: Python Modules
